[
  {
    "id": 1,
    "answer": false,
    "question": "Solen är en planet."
  },
  {
    "id": 2,
    "question": "En ko säger 'muu'.",
    "answer": true
  },
  {
    "id": 3,
    "question": "Spindlar har sex ben.",
    "answer": false
  },
  {
    "id": 4,
    "question": "Stockholm är huvudstaden i Sverige.",
    "answer": true
  },
  {
    "id": 5,
    "question": "En triangel har tre hörn.",
    "answer": true
  },
  {
    "id": 6,
    "question": "Pingviner kan flyga.",
    "answer": false
  },
  {
    "id": 7,
    "question": "Vi andas in syre.",
    "answer": true
  },
  {
    "id": 8,
    "question": "En vecka har åtta dagar.",
    "answer": false
  },
  {
    "id": 9,
    "question": "Pippi Långstrumps häst heter Lilla Gubben.",
    "answer": true
  },
  {
    "id": 10,
    "question": "Is är fryst vatten.",
    "answer": true
  },
  {
    "id": 11,
    "question": "Månen är större än solen.",
    "answer": false
  },
  {
    "id": 12,
    "question": "2 + 2 = 4.",
    "answer": true
  },
  {
    "id": 13,
    "question": "Dinosaurier lever fortfarande.",
    "answer": false
  },
  {
    "id": 14,
    "question": "Fåglar lägger ägg.",
    "answer": true
  },
  {
    "id": 15,
    "question": "En gitarr är ett blåsinstrument.",
    "answer": false
  },
  {
    "id": 16,
    "question": "En timme har 60 minuter.",
    "answer": true
  },
  {
    "id": 17,
    "question": "Mjölk kommer från höns.",
    "answer": false
  },
  {
    "id": 18,
    "question": "Sveriges flagga är gul och blå.",
    "answer": true
  },
  {
    "id": 19,
    "question": "Katter är reptiler.",
    "answer": false
  },
  {
    "id": 20,
    "question": "Hälften av 10 är 5.",
    "answer": true
  },
  {
    "id": 21,
    "question": "Julafton firar vi på sommaren.",
    "answer": false
  },
  {
    "id": 22,
    "question": "En fjäril var först en larv.",
    "answer": true
  },
  {
    "id": 23,
    "question": "Rött ljus betyder 'kör'.",
    "answer": false
  },
  {
    "id": 24,
    "question": "Världens största djur är blåvalen.",
    "answer": true
  },
  {
    "id": 25,
    "question": "Man kan andas under vatten utan hjälpmedel.",
    "answer": false
  },
  {
    "id": 26,
    "question": "Ett piano har tangenter.",
    "answer": true
  },
  {
    "id": 27,
    "question": "Norge är ett grannland till Sverige.",
    "answer": true
  },
  {
    "id": 28,
    "question": "10 x 10 = 100.",
    "answer": true
  },
  {
    "id": 29,
    "question": "En morot är en frukt.",
    "answer": false
  },
  {

    "id": 30,
    "question": "Regn kommer från molnen.",
    "answer": true
  },
  {
    "id": 31,
    "question": "En cirkel är fyrkantig.",
    "answer": false
  },
  {
    "id": 32,
    "question": "Lejon lever vilt i Sverige.",
    "answer": false
  },
  {
    "id": 33,
    "question": "Hjärnan hjälper oss att tänka.",
    "answer": true
  },
  {
    "id": 34,
    "question": "Harry Potter är en riktig person.",
    "answer": false
  },
  {
    "id": 35,
    "question": "Gult och blått blir grönt.",
    "answer": true
  },
  {
    "id": 36,
    "question": "En kvadrat har fem sidor.",
    "answer": false
  },
  {
    "id": 37,
    "question": "En dag har 24 timmar.",
    "answer": true
  },
  {
    "id": 38,
    "question": "Tomten bor på månen.",
    "answer": false
  },
  {
    "id": 39,
    "question": "En bok har sidor.",
    "answer": true
  },
  {
    "id": 40,
    "question": "Eiffeltornet ligger i Sverige.",
    "answer": false
  },
  {
    "id": 41,
    "question": "Träd behöver vatten för att växa.",
    "answer": true
  },
  {
    "id": 42,
    "question": "En val är en fisk.",
    "answer": false
  },
  {
    "id": 43,
    "question": "Ett år har 12 månader.",
    "answer": true
  },
  {
    "id": 44,
    "question": "Snö är varmt.",
    "answer": false
  },
  {
    "id": 45,
    "question": "Ett bibliotek är en plats där man lånar böcker.",
    "answer": true
  },
  {
    "id": 46,
    "question": "5 är ett jämnt tal.",
    "answer": false
  },
  {
    "id": 47,
    "question": "En brandman släcker bränder.",
    "answer": true
  },
  {
    "id": 48,
    "question": "Minecraft är en bok.",
    "answer": false
  },
  {
    "id": 49,
    "question": "Kungen i Sverige heter Carl Gustaf.",
    "answer": true
  },
  {
    "id": 50,
    "question": "Vatten kokar vid 100 grader.",
    "answer": true
  },
  {
    "id": 51,
    "question": "Människor har två hjärtan.",
    "answer": false
  },
  {
    "id": 52,
    "question": "En myra är större än en elefant.",
    "answer": false
  },
  {
    "id": 53,
    "question": "Alfabetet börjar på bokstaven A.",
    "answer": true
  },
  {
    "id": 54,
    "question": "En cykel har tre hjul.",
    "answer": false
  },
  {
    "id": 55,
    "question": "En björn sover vintersömn (går i ide).",
    "answer": true
  },
  {
    "id": 56,
    "question": "Solen går upp i väst.",
    "answer": false
  },
  {
    "id": 57,
    "question": "Vi har fem sinnen.",
    "answer": true
  },
  {
    "id": 58,
    "question": "En orm har fyra ben.",
    "answer": false
  },
  {
    "id": 59,
    "question": "Röd, gul och blå kallas primärfärger.",
    "answer": true
  },
  {
    "id": 60,
    "question": "Man kan äta soppa med en gaffel.",
    "answer": false
  },
  {
    "id": 61,
    "question": "Isbjörnar bor på Nordpolen (Arktis).",
    "answer": true
  },
  {
    "id": 62,
    "question": "10 - 5 = 5.",
    "answer": true
  },
  {
    "id": 63,
    "question": "En doktor jobbar på sjukhus.",
    "answer": true
  },
  {
    "id": 64,
    "question": "En bebiskatt kallas valp.",
    "answer": false
  },
  {
    "id": 65,
    "question": "Emil i Lönneberga täljde trägubbar.",
    "answer": true
  },
  {
    "id": 66,
    "question": "Vikingarna hade horn på sina hjälmar.",
    "answer": false
  },
  {
    "id": 67,
    "question": "Ett verb är ett ord som man kan sätta 'en' eller 'ett' framför.",
    "answer": false
  },
  {
    "id": 68,
    "question": "4 x 5 = 20.",
    "answer": true
  },
  {
    "id": 69,
    "question": "Huvudstaden i Danmark heter Köpenhamn.",
    "answer": true
  },
  {
    "id": 70,
    "question": "Glas är gjort av sand.",
    "answer": true
  },
  {
    "id": 71,
    "question": "Sköldpaddor är snabba.",
    "answer": false
  },
  {
    "id": 72,
    "question": "En insekts kropp har tre delar.",
    "answer": true
  },
  {
    "id": 73,
    "question": "Fotboll spelas med händerna.",
    "answer": false
  },
  {
    "id": 74,
    "question": "Tacos kommer från Sverige.",
    "answer": false
  },
  {
    "id": 75,
    "question": "En zebra har ränder.",
    "answer": true
  },
  {
    "id": 76,
    "question": "Skelettet hjälper till att hålla upp kroppen.",
    "answer": true
  },
  {
    "id": 77,
    "question": "Man firar midsommar på vintern.",
    "answer": false
  },
  {
    "id": 78,
    "question": "Rymden är full av luft.",
    "answer": false
  },
  {
    "id": 79,
    "question": "Jupiter är den största planeten i vårt solsystem.",
    "answer": true
  },
  {
    "id": 80,
    "question": "En bagare bakar bröd.",
    "answer": true
  },
  {
    "id": 81,
    "question": "En fegis kallas ibland för 'badkruka'.",
    "answer": true
  },
  {
    "id": 82,
    "question": "Maneter är fiskar.",
    "answer": false
  },
  {
    "id": 83,
    "question": "Vår planet heter Jorden.",
    "answer": true
  },
  {
    "id": 84,
    "question": "Ett decennium är 100 år.",
    "answer": false
  },
  {
    "id": 85,
    "question": "En groda var först ett grodyngel.",
    "answer": true
  },
  {
    "id": 86,
    "question": "3 + 3 + 3 = 9.",
    "answer": true
  },
  {
    "id": 87,
    "question": "Pyramiderna finns i Kina.",
    "answer": false
  },
  {
    "id": 88,
    "question": "En delfin är ett däggdjur.",
    "answer": true
  },
  {
    "id": 89,
    "question": "Bokstaven 'S' är en vokal.",
    "answer": false
  },
  {
    "id": 90,
    "question": "Kängurur lever i Australien.",
    "answer": true
  },
  {
    "id": 91,
    "question": "En kock lagar bilar.",
    "answer": false
  },
  {
    "id": 92,
    "question": "Myggor är insekter.",
    "answer": true
  },
  {
    "id": 93,
    "question": "Påsken är alltid i december.",
    "answer": false
  },
  {
    "id": 94,
    "question": "Hajar lever i havet.",
    "answer": true
  },
  {
    "id": 95,
    "question": "Man kan se Kinesiska muren från månen.",
    "answer": false
  },
  {
    "id": 96,
    "question": "En polis hjälper människor.",
    "answer": true
  },
  {
    "id": 97,
    "question": "Vatten kan vara i fast form (is), flytande form och gasform (ånga).",
    "answer": true
  },
  {
    "id": 98,
    "question": "100 är mindre än 10.",
    "answer": false
  },
  {
    "id": 99,
    "question": "En snigel är ett av de snabbaste djuren.",
    "answer": false
  },
  {
    "id": 100,
    "question": "Alfabetet slutar på bokstaven Ö.",
    "answer": true
  }
]